lark_dbml/__init__.py
lark_dbml/__version__.py
lark_dbml/dbml.lark
lark_dbml/lark_dbml_standalone.py
lark_dbml/schema.py
lark_dbml/transformer.py
lark_dbml/converter/__init__.py
lark_dbml/converter/datacontract/__init__.py
lark_dbml/converter/datacontract/base.py
lark_dbml/converter/datacontract/column.py
lark_dbml/converter/datacontract/enum.py
lark_dbml/converter/datacontract/note.py
lark_dbml/converter/datacontract/project.py
lark_dbml/converter/datacontract/reference.py
lark_dbml/converter/datacontract/table.py
lark_dbml/converter/dbml/__init__.py
lark_dbml/converter/dbml/base.py
lark_dbml/converter/dbml/column.py
lark_dbml/converter/dbml/enum.py
lark_dbml/converter/dbml/index.py
lark_dbml/converter/dbml/note.py
lark_dbml/converter/dbml/project.py
lark_dbml/converter/dbml/reference.py
lark_dbml/converter/dbml/table.py
lark_dbml/converter/dbml/table_group.py
lark_dbml/converter/dbml/utils.py
lark_dbml/converter/mermaid/__init__.py
lark_dbml/converter/mermaid/base.py
lark_dbml/converter/mermaid/column.py
lark_dbml/converter/mermaid/enum.py
lark_dbml/converter/mermaid/note.py
lark_dbml/converter/mermaid/project.py
lark_dbml/converter/mermaid/reference.py
lark_dbml/converter/mermaid/table.py
lark_dbml/converter/mermaid/table_group.py
lark_dbml/converter/sql/__init__.py
lark_dbml/converter/sql/base.py
lark_dbml/converter/sql/column.py
lark_dbml/converter/sql/enum.py
lark_dbml/converter/sql/index.py
lark_dbml/converter/sql/reference.py
lark_dbml/converter/sql/table.py
lark_dbml-0.7.0.dist-info/licenses/LICENSE
lark_dbml-0.7.0.dist-info/METADATA
lark_dbml-0.7.0.dist-info/WHEEL
lark_dbml-0.7.0.dist-info/top_level.txt
lark_dbml-0.7.0.dist-info/RECORD
