Metadata-Version: 2.4
Name: lark-dbml
Version: 0.7.0
Summary: DBML parser using Lark.
Author-email: Austin Huynh <contact@austinhuynh.me>
License-Expression: MIT
Project-URL: Homepage, https://github.com/daihuynh/lark-dbml
Project-URL: Bug Tracker, https://github.com/daihuynh/lark-dbml/issues
Keywords: dbml,lark,sql,ddl,data contract,pydantic,parser,lalr,earley,standalone
Classifier: Development Status :: 4 - Beta
Classifier: Programming Language :: Python :: 3
Classifier: Operating System :: OS Independent
Classifier: Intended Audience :: Developers
Classifier: Topic :: Text Processing
Classifier: Topic :: Software Development :: Code Generators
Requires-Python: >=3.10
License-File: LICENSE
Requires-Dist: pydantic~=2.11
Provides-Extra: sql
Requires-Dist: sqlglot>=27.0.0; extra == "sql"
Provides-Extra: lark
Requires-Dist: lark>=1.2.2; extra == "lark"
Dynamic: license-file
